deluge_announce/__init__.py
deluge_announce/announcer.py
deluge_announce/config.py
deluge_announce/enums.py
deluge_announce/logger.py
deluge_announce-0.1.4.dist-info/LICENSE
deluge_announce-0.1.4.dist-info/METADATA
deluge_announce-0.1.4.dist-info/WHEEL
deluge_announce-0.1.4.dist-info/RECORD
