Metadata-Version: 2.3
Name: deluge-announce
Version: 0.1.4
Summary: Simple utility to re-announce torrents for Deluge on a timed interval (single run or indefinitely via CRON)
License: MIT
Keywords: python,deluge,re-announce,announce
Author: jlw_4049
Author-email: jessielw4049@gmail.com
Maintainer: jlw_4049
Maintainer-email: jessielw4049@gmail.com
Requires-Python: >=3.10
Classifier: Development Status :: 5 - Production/Stable
Classifier: Environment :: Console
Classifier: Intended Audience :: Developers
Classifier: License :: OSI Approved :: MIT License
Classifier: Operating System :: OS Independent
Classifier: Programming Language :: Python :: 3
Classifier: Programming Language :: Python :: 3.10
Classifier: Programming Language :: Python :: 3.11
Classifier: Programming Language :: Python :: 3.12
Classifier: Programming Language :: Python :: 3.13
Classifier: Programming Language :: Python :: 3 :: Only
Classifier: Programming Language :: Python :: Implementation :: CPython
Classifier: Topic :: Utilities
Requires-Dist: apscheduler (>=3.11.0,<4.0.0)
Requires-Dist: deluge-web-client (>=1.0.4,<2.0.0)
Requires-Dist: python-dotenv (>=1.0.1,<2.0.0)
